macagent_core/__init__.py
macagent_core/audit.py
macagent_core/cli.py
macagent_core/hardware.py
macagent_core-1.2.0.dist-info/licenses/LICENSE
macagent_core-1.2.0.dist-info/METADATA
macagent_core-1.2.0.dist-info/WHEEL
macagent_core-1.2.0.dist-info/entry_points.txt
macagent_core-1.2.0.dist-info/top_level.txt
macagent_core-1.2.0.dist-info/RECORD
