Metadata-Version: 2.4
Name: macagent-core
Version: 1.2.0
Summary: MacAgent Core - Free, open-source AI orchestration for macOS
Author-email: Dallas McMillan <dallas@macagent.pro>
License: MIT
Project-URL: Homepage, https://macagent.pro
Project-URL: Repository, https://github.com/midnightnow/macagent
Project-URL: Documentation, https://github.com/midnightnow/macagent#readme
Project-URL: Bug Tracker, https://github.com/midnightnow/macagent/issues
Project-URL: Pro Version, https://macagent.pro
Keywords: ai,agent,macos,automation,llm,siri
Classifier: Development Status :: 4 - Beta
Classifier: Environment :: MacOS X
Classifier: Operating System :: MacOS
Classifier: Programming Language :: Python :: 3
Classifier: Programming Language :: Python :: 3.9
Classifier: Programming Language :: Python :: 3.10
Classifier: Programming Language :: Python :: 3.11
Classifier: Programming Language :: Python :: 3.12
Classifier: Topic :: Scientific/Engineering :: Artificial Intelligence
Classifier: License :: OSI Approved :: MIT License
Requires-Python: >=3.9
License-File: LICENSE
Provides-Extra: full
Requires-Dist: psutil>=5.9.0; extra == "full"
Dynamic: license-file
